beeminder_sync/__init__.py
beeminder_sync/beeminder_sync.py
beeminder_sync/cli.py
beeminder_sync/logger.py
beeminder_sync/config/config_template.ini
beeminder_sync-0.2.0.dist-info/METADATA
beeminder_sync-0.2.0.dist-info/RECORD
beeminder_sync-0.2.0.dist-info/WHEEL
beeminder_sync-0.2.0.dist-info/entry_points.txt
beeminder_sync-0.2.0.dist-info/top_level.txt
