Metadata-Version: 2.1
Name: beeminder-sync
Version: 0.2.0
Summary: A python CLI to sync various datasources with Beeminder
Home-page: https://github.com/dileep-kishore/beeminder_sync
Author: Dileep Kishore
Author-email: k.dileep1994@gmail.com
License: MIT license
Keywords: beeminder_sync
Platform: UNKNOWN
Classifier: Development Status :: 2 - Pre-Alpha
Classifier: Intended Audience :: Developers
Classifier: License :: OSI Approved :: MIT License
Classifier: Natural Language :: English
Classifier: Programming Language :: Python :: 3.6
Requires-Dist: requests
Requires-Dist: click
Requires-Dist: halo
Requires-Dist: furl
Requires-Dist: maya
Requires-Dist: pyjq
